odoo/addons/pos_lot_selection/README.rst
odoo/addons/pos_lot_selection/__init__.py
odoo/addons/pos_lot_selection/__manifest__.py
odoo/addons/pos_lot_selection/i18n/ca.po
odoo/addons/pos_lot_selection/i18n/es.po
odoo/addons/pos_lot_selection/i18n/pos_lot_selection.pot
odoo/addons/pos_lot_selection/static/description/icon.png
odoo/addons/pos_lot_selection/static/src/css/pos.css
odoo/addons/pos_lot_selection/static/src/js/chrome.js
odoo/addons/pos_lot_selection/static/src/js/models.js
odoo/addons/pos_lot_selection/static/src/xml/pos.xml
odoo/addons/pos_lot_selection/templates/assets.xml
odoo11_addon_pos_lot_selection-11.0.1.0.0.99.dev5.dist-info/METADATA
odoo11_addon_pos_lot_selection-11.0.1.0.0.99.dev5.dist-info/WHEEL
odoo11_addon_pos_lot_selection-11.0.1.0.0.99.dev5.dist-info/top_level.txt
odoo11_addon_pos_lot_selection-11.0.1.0.0.99.dev5.dist-info/RECORD
